mikebedingfield/__init__.py
mikebedingfield/__main__.py
mikebedingfield/speaker.py
mikebedingfield/speakers/__init__.py
mikebedingfield/speakers/mike.py
mikebedingfield-0.2.0.dist-info/licenses/LICENSE.txt
mikebedingfield-0.2.0.dist-info/METADATA
mikebedingfield-0.2.0.dist-info/WHEEL
mikebedingfield-0.2.0.dist-info/entry_points.txt
mikebedingfield-0.2.0.dist-info/top_level.txt
mikebedingfield-0.2.0.dist-info/RECORD
