Metadata-Version: 2.4
Name: mikebedingfield
Version: 0.2.0
Summary: My first package!
Author-email: C5m7b4 <C5m7b4@gmail.com>
Maintainer-email: C5m7b4 <C5m7b4@gmail.com>
License: Copyright 2026  C5m7b4
Project-URL: Homepage, https://github.com/C5m7b4/mikebedingfield
Project-URL: Documentation, https://github.com/C5m7b4/mikebedingfield/README.md
Keywords: mbedingfield
Classifier: Programming Language :: Python :: 3.9
Classifier: Programming Language :: Python :: Implementation :: CPython
Classifier: License :: OSI Approved :: BSD License
Classifier: Intended Audience :: Developers
Classifier: Operating System :: POSIX :: Linux
Classifier: Operating System :: Microsoft :: Windows
Classifier: Operating System :: MacOS
Classifier: Operating System :: MacOS :: MacOS X
Requires-Python: >=3.9
License-File: LICENSE.txt
Requires-Dist: colorama~=0.0
Dynamic: license-file
